SeleniumExtensionLibrary/SeleniumExtensionLibrary.py
SeleniumExtensionLibrary/__init__.py
SeleniumExtensionLibrary/version.py
rf_seleniumextensionlibrary-0.3.2.dist-info/LICENSE
rf_seleniumextensionlibrary-0.3.2.dist-info/METADATA
rf_seleniumextensionlibrary-0.3.2.dist-info/WHEEL
rf_seleniumextensionlibrary-0.3.2.dist-info/top_level.txt
rf_seleniumextensionlibrary-0.3.2.dist-info/RECORD
