Metadata-Version: 2.1
Name: rf-seleniumextensionlibrary
Version: 0.3.2
Summary: Selenium Extension Library
Home-page: https://github.com/MainSystemDev/rf-seleniumextensionlibray
Author: Shiela Buitizon
Author-email: shiela.buitizon@mnltechnology.com
License: Type license() to see the full license text
Platform: any
Classifier: Development Status :: 5 - Production/Stable
Classifier: License :: OSI Approved :: MIT License
Classifier: Operating System :: OS Independent
Classifier: Programming Language :: Python :: 3
Classifier: Topic :: Software Development :: Testing
Classifier: Framework :: Robot Framework
Classifier: Framework :: Robot Framework :: Library
Requires-Dist: browsermob-proxy (==0.8.0)
Requires-Dist: image (==1.5.28)
Requires-Dist: psutil (==5.7.0)
Requires-Dist: robotframework-seleniumlibrary (>=4.5.0)
